{"stat.walkOneCm":4463,"stat.drop.minecraft.rotten_flesh":22,"stat.leaveGame":4,"stat.useItem.minecraft.diamond_axe":17,"stat.drop.minecraft.shield":1,"stat.drop.minecraft.spawn_egg":64,"stat.jump":51,"stat.swimOneCm":37,"stat.crouchOneCm":239,"stat.sprintOneCm":8809,"stat.pickup.minecraft.rotten_flesh":5,"stat.useItem.minecraft.wooden_shovel":5,"stat.mobKills":14,"stat.drop.minecraft.golden_apple":126,"stat.flyOneCm":301050,"stat.drop":7,"stat.playOneMinute":12589,"stat.useItem.minecraft.wooden_sword":161,"stat.sneakTime":4,"stat.useItem.minecraft.stone_sword":1,"stat.damageDealt":1873,"stat.killEntity.Zombie":9,"stat.timeSinceDeath":12589,"stat.useItem.minecraft.spawn_egg":14}