{"stat.pickup.minecraft.rotten_flesh":18,"stat.walkOneCm":1192,"stat.drop.minecraft.rotten_flesh":18,"stat.pickup.minecraft.grass":2,"stat.killEntity.Spider":2,"stat.killEntity.Husk":13,"stat.pickup.minecraft.stone_sword":1,"stat.mobKills":16,"stat.talkedToVillager":6,"stat.pickup.minecraft.string":6,"stat.flyOneCm":34967,"stat.drop":18,"stat.jump":372,"stat.swimOneCm":2278,"stat.pickup.minecraft.potato":1,"stat.playOneMinute":10056,"stat.drop.minecraft.string":5,"stat.drop.minecraft.carrot":2,"stat.pickup.minecraft.carrot":4,"stat.useItem.minecraft.stone_sword":328,"stat.sneakTime":5,"stat.drop.minecraft.stone_sword":1,"stat.damageDealt":6392,"stat.killEntity.Zombie":1,"stat.timeSinceDeath":10056,"stat.drop.minecraft.potato":1,"stat.drop.minecraft.shears":1,"stat.sprintOneCm":1457,"stat.useItem.minecraft.spawn_egg":16,"stat.useItem.minecraft.stone_slab2":2,"stat.drop.minecraft.grass":3,"stat.diveOneCm":273}