{"stat.pickup.minecraft.rotten_flesh":1,"stat.killEntity.Skeleton":1,"stat.useItem.minecraft.splash_potion":7,"stat.walkOneCm":3236,"stat.pickup.minecraft.bone":2,"stat.leaveGame":2,"stat.pickup.minecraft.arrow":1,"stat.killEntity.Husk":1,"stat.mobKills":5,"stat.useItem.minecraft.diamond_sword":28,"stat.flyOneCm":33035,"stat.jump":71,"stat.playOneMinute":5055,"stat.useItem.minecraft.wooden_sword":36,"stat.sneakTime":4,"stat.damageDealt":1128,"stat.killEntity.Zombie":2,"stat.timeSinceDeath":5055,"stat.sprintOneCm":7152,"stat.useItem.minecraft.spawn_egg":5}