{"stat.walkOneCm":8418,"stat.pickup.minecraft.bone":2,"stat.leaveGame":1,"stat.pickup.minecraft.arrow":5,"stat.useItem.minecraft.diamond_sword":47,"stat.pickup.minecraft.string":1,"stat.jump":41,"stat.swimOneCm":561,"stat.fallOneCm":2878,"stat.entityKilledBy.Skeleton":2,"stat.crouchOneCm":73,"stat.pickup.minecraft.dirt":2,"stat.useItem.minecraft.dirt":1,"stat.sprintOneCm":3006,"stat.useItem.minecraft.stone_slab2":2,"stat.pickup.minecraft.rotten_flesh":4,"stat.killEntity.Skeleton":2,"stat.damageTaken":670,"stat.killEntity.Spider":1,"stat.drop.minecraft.bone":2,"stat.mobKills":10,"stat.useItem.minecraft.golden_apple":1,"stat.flyOneCm":16487,"stat.deaths":2,"stat.drop":7,"stat.pickup.minecraft.wheat_seeds":3,"stat.playOneMinute":23496,"stat.drop.minecraft.wheat_seeds":2,"stat.sneakTime":55,"stat.damageDealt":1748,"stat.drop.minecraft.arrow":4,"stat.killEntity.Zombie":6,"stat.timeSinceDeath":10257,"stat.killEntity.Cow":1,"stat.useItem.minecraft.spawn_egg":9,"stat.mineBlock.minecraft.tallgrass":9,"stat.diveOneCm":279}